sqlajdbc/__init__.py
sqlajdbc/sqlajdbc.py
sqlalchemy_jdbc_generic-0.1.dev10.dist-info/LICENSE.txt
sqlalchemy_jdbc_generic-0.1.dev10.dist-info/METADATA
sqlalchemy_jdbc_generic-0.1.dev10.dist-info/WHEEL
sqlalchemy_jdbc_generic-0.1.dev10.dist-info/entry_points.txt
sqlalchemy_jdbc_generic-0.1.dev10.dist-info/top_level.txt
sqlalchemy_jdbc_generic-0.1.dev10.dist-info/RECORD
