Metadata-Version: 2.1
Name: sqlalchemy-jdbc-generic
Version: 0.1.dev10
Summary: Universal JDBC Dialect for SQLAlchemy
Home-page: https://github.com/bwadle/sqlalchemy-jdbc-generic
Author: Bryce Wadle
Author-email: brycew@att.com
License: AT&T BSD
Project-URL: Documentation, https://github.com/bwadle/sqlalchemy-jdbc-generic
Project-URL: Source, https://github.com/bwadle/sqlalchemy-jdbc-generic
Project-URL: Issues, https://github.com/bwadle/sqlalchemy-jdbc-generic/issues
Keywords: sqlalchemy jdbc database db sql java jpype dialect
Platform: any
Classifier: Development Status :: 4 - Beta
Classifier: Environment :: Console
Classifier: Environment :: Other Environment
Classifier: Intended Audience :: Developers
Classifier: Intended Audience :: System Administrators
Classifier: Intended Audience :: Information Technology
Classifier: License :: OSI Approved :: BSD License
Classifier: Operating System :: OS Independent
Classifier: Programming Language :: Python :: 3
Classifier: Programming Language :: Python :: 3 :: Only
Classifier: Programming Language :: SQL
Classifier: Topic :: Database
Classifier: Topic :: Scientific/Engineering :: Information Analysis
Classifier: Topic :: Software Development :: Libraries
Classifier: Topic :: Software Development :: Libraries :: Python Modules
License-File: LICENSE.txt
Requires-Dist: sqlalchemy
Requires-Dist: jaydebeapi
